LICENSE
README.md
pyproject.toml
omnicomm/__init__.py
omnicomm/commands.py
omnicomm/exceptions.py
omnicomm/protocol.py
omnicomm/registry.py
omnicomm/settings.py
omnicomm/types.py
omnicomm/utils.py
omnicomm/aliases/__init__.py
omnicomm/aliases/commands.py
omnicomm/proto/__init__.py
omnicomm/proto/profi2_optim2_lite2.proto
omnicomm/proto/profi2_optim2_lite2_pb2.py
omnicomm/proto/profi_optim_lite.proto
omnicomm/proto/profi_optim_lite_pb2.py
omnicomm/tests/__init__.py
omnicomm/tests/test_command.py
omnicomm/tests/test_protocol.py
omnicomm/tests/test_registry.py
omnicomm/tests/test_server.py
omnicomm/tests/test_utils.py
omnicomm-0.4.1.dist-info/METADATA
omnicomm-0.4.1.dist-info/WHEEL
omnicomm-0.4.1.dist-info/licenses/LICENSE
omnicomm-0.4.1.dist-info/RECORD
