Metadata-Version: 2.3
Name: omnicomm
Version: 0.4.1
Summary: Implementation of the Omnicomm protocol
Project-URL: Documentation, https://github.com/pikhovkin/omnicomm#readme
Project-URL: Issues, https://github.com/pikhovkin/omnicomm/issues
Project-URL: Source, https://github.com/pikhovkin/omnicomm
Author-email: Sergei Pikhovkin <s@pikhovkin.ru>
License-Expression: MIT
License-File: LICENSE
Keywords: monitoring,network,omnicomm,omnicomm-protocol,protobuf,protocol,tcp,tcp-protocol
Classifier: Development Status :: 2 - Pre-Alpha
Classifier: License :: OSI Approved :: MIT License
Classifier: Programming Language :: Python
Classifier: Programming Language :: Python :: 3 :: Only
Classifier: Programming Language :: Python :: 3.10
Classifier: Programming Language :: Python :: 3.11
Classifier: Programming Language :: Python :: 3.12
Classifier: Topic :: System :: Monitoring
Classifier: Topic :: Utilities
Requires-Python: >=3.10
Requires-Dist: libscrc
Requires-Dist: protobuf==3.20.3
